sphinxjp.themes.sphinxjp-1.0.2-py3.7-nspkg.pth
sphinxjp/themes/sphinxjp/__init__.py
sphinxjp/themes/sphinxjp/templates/sphinxjp/footer.html
sphinxjp/themes/sphinxjp/templates/sphinxjp/globalnavigation.html
sphinxjp/themes/sphinxjp/templates/sphinxjp/globaltoc.html
sphinxjp/themes/sphinxjp/templates/sphinxjp/layout.html
sphinxjp/themes/sphinxjp/templates/sphinxjp/localtoc.html
sphinxjp/themes/sphinxjp/templates/sphinxjp/page.html
sphinxjp/themes/sphinxjp/templates/sphinxjp/relations.html
sphinxjp/themes/sphinxjp/templates/sphinxjp/search.html
sphinxjp/themes/sphinxjp/templates/sphinxjp/searchbox.html
sphinxjp/themes/sphinxjp/templates/sphinxjp/sourcelink.html
sphinxjp/themes/sphinxjp/templates/sphinxjp/theme.conf
sphinxjp/themes/sphinxjp/templates/sphinxjp/static/HatenaBookmark.js
sphinxjp/themes/sphinxjp/templates/sphinxjp/static/basic.css
sphinxjp/themes/sphinxjp/templates/sphinxjp/static/docBg.png
sphinxjp/themes/sphinxjp/templates/sphinxjp/static/document.css
sphinxjp/themes/sphinxjp/templates/sphinxjp/static/footer_bg.png
sphinxjp/themes/sphinxjp/templates/sphinxjp/static/general.css
sphinxjp/themes/sphinxjp/templates/sphinxjp/static/gnav_bg.png
sphinxjp/themes/sphinxjp/templates/sphinxjp/static/gnav_btn_doc.png
sphinxjp/themes/sphinxjp/templates/sphinxjp/static/gnav_home.png
sphinxjp/themes/sphinxjp/templates/sphinxjp/static/gnav_mod.png
sphinxjp/themes/sphinxjp/templates/sphinxjp/static/header_bg.png
sphinxjp/themes/sphinxjp/templates/sphinxjp/static/header_btn.png
sphinxjp/themes/sphinxjp/templates/sphinxjp/static/highlight.css
sphinxjp/themes/sphinxjp/templates/sphinxjp/static/index.css
sphinxjp/themes/sphinxjp/templates/sphinxjp/static/logo.png
sphinxjp/themes/sphinxjp/templates/sphinxjp/static/next.png
sphinxjp/themes/sphinxjp/templates/sphinxjp/static/prev.png
sphinxjp/themes/sphinxjp/templates/sphinxjp/static/reset.css
sphinxjp/themes/sphinxjp/templates/sphinxjp/static/search.png
sphinxjp/themes/sphinxjp/templates/sphinxjp/static/show_source.png
sphinxjp.themes.sphinxjp-1.0.2.dist-info/AUTHORS.rst
sphinxjp.themes.sphinxjp-1.0.2.dist-info/LICENSE.txt
sphinxjp.themes.sphinxjp-1.0.2.dist-info/METADATA
sphinxjp.themes.sphinxjp-1.0.2.dist-info/WHEEL
sphinxjp.themes.sphinxjp-1.0.2.dist-info/entry_points.txt
sphinxjp.themes.sphinxjp-1.0.2.dist-info/namespace_packages.txt
sphinxjp.themes.sphinxjp-1.0.2.dist-info/top_level.txt
sphinxjp.themes.sphinxjp-1.0.2.dist-info/RECORD
