Metadata-Version: 2.1
Name: sphinxjp.themes.sphinxjp
Version: 1.0.2
Summary: A sphinx theme for sphinx-users.jp site.
Home-page: https://github.com/sphinxjp/sphinxjp.themes.sphinxjp
Author: sphinx-users.jp
Author-email: shimizukawa@gmail.com
License: MIT
Keywords: sphinx,reStructuredText,theme
Platform: UNKNOWN
Classifier: Development Status :: 5 - Production/Stable
Classifier: License :: OSI Approved :: MIT License
Classifier: Programming Language :: Python
Classifier: Programming Language :: Python :: 2
Classifier: Programming Language :: Python :: 3
Classifier: Topic :: Software Development
Classifier: Topic :: Software Development :: Documentation
Classifier: Topic :: Text Processing :: Markup
Classifier: Framework :: Sphinx
Classifier: Framework :: Sphinx :: Theme
Requires-Dist: setuptools
Requires-Dist: sphinx (>=1.6)
